dse_do_dashboard/__init__.py
dse_do_dashboard/dash_app.py
dse_do_dashboard/dash_plotly_manager.py
dse_do_dashboard/do_dash_app.py
dse_do_dashboard/version.py
dse_do_dashboard/__pycache__/__init__.cpython-310.pyc
dse_do_dashboard/__pycache__/do_dash_app.cpython-310.pyc
dse_do_dashboard/__pycache__/version.cpython-310.pyc
dse_do_dashboard/main_pages/__init__.py
dse_do_dashboard/main_pages/explore_solution_page.py
dse_do_dashboard/main_pages/home_page.py
dse_do_dashboard/main_pages/home_page_edit.py
dse_do_dashboard/main_pages/main_page.py
dse_do_dashboard/main_pages/not_found.py
dse_do_dashboard/main_pages/prepare_data_page.py
dse_do_dashboard/main_pages/prepare_data_page_edit.py
dse_do_dashboard/main_pages/run_model_page.py
dse_do_dashboard/main_pages/run_model_page_old.py
dse_do_dashboard/main_pages/visualization_tabs_page.py
dse_do_dashboard/utils/__init__.py
dse_do_dashboard/utils/dash_common_utils.py
dse_do_dashboard/utils/domodelrunner.py
dse_do_dashboard/utils/domodelrunner_old.py
dse_do_dashboard/utils/donotebookrunner.py
dse_do_dashboard/utils/scenariodbmanager_update.py
dse_do_dashboard/visualization_pages/__init__.py
dse_do_dashboard/visualization_pages/folium_column_visualization_page.py
dse_do_dashboard/visualization_pages/kpi_compare_page.py
dse_do_dashboard/visualization_pages/kpi_page_template.py
dse_do_dashboard/visualization_pages/plotly_1_column_visualization_page.py
dse_do_dashboard/visualization_pages/plotly_rows_visualization_page.py
dse_do_dashboard/visualization_pages/visualization_page.py
dse_do_dashboard/visualization_pages/__pycache__/__init__.cpython-310.pyc
dse_do_dashboard/visualization_pages/__pycache__/plotly_1_column_visualization_page.cpython-310.pyc
dse_do_dashboard/visualization_pages/__pycache__/visualization_page.cpython-310.pyc
dse_do_dashboard-0.1.2.3.dist-info/LICENSE
dse_do_dashboard-0.1.2.3.dist-info/METADATA
dse_do_dashboard-0.1.2.3.dist-info/WHEEL
dse_do_dashboard-0.1.2.3.dist-info/top_level.txt
dse_do_dashboard-0.1.2.3.dist-info/RECORD
