Metadata-Version: 2.1
Name: dse-do-dashboard
Version: 0.1.2.3
Summary: Decision Optimization Dashboard for IBM Cloud Pak for Data DO projects
Home-page: https://github.com/IBM/dse-do-dashboard
Author: Victor Terpstra
Author-email: vterpstra@us.ibm.com
License: UNKNOWN
Project-URL: Source, https://github.com/IBM/dse-do-dashboard
Project-URL: Documentation, https://ibm.github.io/dse-do-dashboard/
Project-URL: IBM Decision Optimization, https://www.ibm.com/analytics/decision-optimization
Platform: UNKNOWN
Classifier: Development Status :: 4 - Beta
Classifier: Programming Language :: Python :: 3.8
Classifier: License :: OSI Approved :: Apache Software License
Classifier: Operating System :: OS Independent
Classifier: Topic :: Documentation :: Sphinx
License-File: LICENSE
Requires-Dist: dse-do-utils (>=0.5.4.2)
Requires-Dist: dash
Requires-Dist: flask-caching
Requires-Dist: dash-bootstrap-components
Requires-Dist: dash-bootstrap-templates
Requires-Dist: dash-pivottable
Requires-Dist: dash-daq
Requires-Dist: sqlalchemy (>=1.3.23)
Requires-Dist: pandas
Requires-Dist: plotly
Requires-Dist: openpyxl
Requires-Dist: diskcache
Requires-Dist: multiprocess
Requires-Dist: psutil
